[
    {
        "ID": 1759,
        "fields": {
            "driver": {
                "status": {
                    "value": "expired_documents",
                    "label": "Expired documents"
                },
                "date": "01\/24\/2025 10:00 am",
                "availability": "San Joaquin County_California, CA",
                "top_driver": false,
                "paid": true,
                "owner_driver": "Nelson Eguizabal",
                "owner_phone": "(408) 728-3842",
                "owner_home_city": "Tracy",
                "owner_email": "nelson.eguizabal@gmail.com",
                "owner_home": "California, CA",
                "type": "Cargo van",
                "lwh": "120\/55\/66",
                "payload_max": "4000",
                "city": "Tracy",
                "comments": "(408) 421-9213 -  second phone number for tracking purposes (without MC)-JA\r\nhe is veteran, can fast pass the security check in the military base- NA\r\n\r\n03\/17 JD:  I&#39;m currently out of the country due to family health issues. I should be back by next month, hopefully.",
                "vin_code": "3C6TRVCG4LE139575",
                "residentship": "USA Passport",
                "driver_name": "Nelson Eguizabal",
                "driver_phone": "(408) 728-3842",
                "driver_email": "nelson.eguizabal@gmail.com",
                "driver2_name": "Nelson Eguizabal (emergency)",
                "driver2_phone": "(408) 421-9213",
                "driver2_email": "",
                "main_contact": "(408) 728-3842",
                "driver_license": "D3024843",
                "ein": "92-3132142",
                "company_name": "OTR VAN LLC",
                "vehicle_year": "2020",
                "date_hr": "02\/05\/2024 6:28 pm",
                "id_hr": false,
                "source_hr": "betterteam",
                "nationality": "American",
                "google_drive": true,
                "emergency_contact": "Abril Eguizabal",
                "emergency_phone": "(408) 701-7804",
                "select_labels": [
                    "hazmat",
                    "tsa",
                    "twic",
                    "ppe",
                    "e-track",
                    "canada",
                    "real_id",
                    "macropoint",
                    "tucker-tools",
                    "printer"
                ],
                "select_labels_distance": [
                    "any"
                ],
                "preferred_language_icon": "en"
            },
            "latitude": "37.737191",
            "longitude": "-121.433384",
            "updated_zipcode": "01\/24\/2025 5:50 am",
            "zipcode": "95376",
            "timecode": "1737741007",
            "last_update": "Last update: Julia Donovan - 03\/17\/2025 12:59 pm",
            "date_timecode": "1737712800",
            "driver_rating": "[{\"name\":\"Victor Miller\",\"time\":1708474620,\"reit\":\"2\",\"mess\":\"Did a partial on the load. Load was CACA and he drove to OREGON at night and then came back to CA  delivered between timeframes. However he was tracking on macro with us and if it was a load when broker sends tracking  we39d have been in big troubles. HR should talk to him and expain that we can39t do partial unless agreed before. \",\"order_number\":\"34045\"},{\"name\":\"Vlad Allen\",\"time\":1708832640,\"reit\":\"5\",\"mess\":\"Good communications with the dispatcher.\",\"order_number\":\"90156\"},{\"name\":\"Victor Miller\",\"time\":1709163780,\"reit\":\"5\",\"mess\":\"\",\"order_number\":\"34121 \"},{\"name\":\"Victor Miller\",\"time\":1709163780,\"reit\":\"5\",\"mess\":\"\",\"order_number\":\"34192\"},{\"name\":\"Vlad Allen\",\"time\":1709226660,\"reit\":\"5\",\"mess\":\"\",\"order_number\":\"8362692\"},{\"name\":\"Victor Miller\",\"time\":1709314920,\"reit\":\"5\",\"mess\":\"\",\"order_number\":\"34278\"},{\"name\":\"Jacob Kowalski\",\"time\":1711651140,\"reit\":\"5\",\"mess\":\"\",\"order_number\":\"1633427\"},{\"name\":\"Travis McMillan\",\"time\":1711653000,\"reit\":\"5\",\"mess\":\"Awesome Rate on the local hazmat. Awesome updates. Awesome Timing.\",\"order_number\":\"554574\"},{\"name\":\"Jake Freedman\",\"time\":1711742760,\"reit\":\"5\",\"mess\":\"Good rate good communication good timing assisted like a boss\",\"order_number\":\"1547786\"},{\"name\":\"Tracking \",\"time\":1712330040,\"reit\":\"5\",\"mess\":\"\",\"order_number\":\"34796 \"},{\"name\":\"Victor Miller\",\"time\":1712330100,\"reit\":\"5\",\"mess\":\"\",\"order_number\":\"34796 \"},{\"name\":\"Jacob Kowalski\",\"time\":1714082340,\"reit\":\"5\",\"mess\":\"\",\"order_number\":\"146244\"},{\"name\":\"Terry Abdulaev\",\"time\":1714481940,\"reit\":\"5\",\"mess\":\"\",\"order_number\":\"14775370\"},{\"name\":\"Vlad Allen\",\"time\":1714492320,\"reit\":\"5\",\"mess\":\"\",\"order_number\":\"1023853\"},{\"name\":\"Vlad Allen\",\"time\":1714492320,\"reit\":\"5\",\"mess\":\"\",\"order_number\":\"6702813\"},{\"name\":\"Vlad Allen\",\"time\":1714492320,\"reit\":\"5\",\"mess\":\"\",\"order_number\":\"8711613\"},{\"name\":\"Vlad Allen\",\"time\":1714492380,\"reit\":\"5\",\"mess\":\"\",\"order_number\":\"9888568\"},{\"name\":\"Vlad Allen\",\"time\":1714492380,\"reit\":\"5\",\"mess\":\"\",\"order_number\":\"7813808\"},{\"name\":\"Dan Vilkovsky\",\"time\":1714499220,\"reit\":\"5\",\"mess\":\"Gold rate. Perfect job.\",\"order_number\":\"6863\"},{\"name\":\"Victor Miller\",\"time\":1714499820,\"reit\":\"5\",\"mess\":\"\",\"order_number\":\"34939\"},{\"name\":\"Victor Miller\",\"time\":1715095320,\"reit\":\"5\",\"mess\":\"\",\"order_number\":\"35472\"},{\"name\":\"Terry Abdulaev\",\"time\":1717005120,\"reit\":\"5\",\"mess\":\"\",\"order_number\":\"LDS14628881\"},{\"name\":\"Eric Mayson\",\"time\":1717006260,\"reit\":\"5\",\"mess\":\"\",\"order_number\":\"1328197\"},{\"name\":\"Vlad Allen\",\"time\":1717110300,\"reit\":\"5\",\"mess\":\"\",\"order_number\":\"119113904\"},{\"name\":\"Vlad Allen\",\"time\":1717110360,\"reit\":\"5\",\"mess\":\"\",\"order_number\":\"4980231\"},{\"name\":\"Vlad Allen\",\"time\":1717110360,\"reit\":\"5\",\"mess\":\"\",\"order_number\":\"1567258\"},{\"name\":\"Vlad Allen\",\"time\":1717110360,\"reit\":\"5\",\"mess\":\"\",\"order_number\":\"119037924\"},{\"name\":\"Vlad Allen\",\"time\":1717110360,\"reit\":\"5\",\"mess\":\"\",\"order_number\":\"119016802\"},{\"name\":\"Ben Silver\",\"time\":1717187580,\"reit\":\"5\",\"mess\":\"\",\"order_number\":\"7591444\"},{\"name\":\"James Price\",\"time\":1717810860,\"reit\":\"5\",\"mess\":\"great service and rate \",\"order_number\":\"0658245\"},{\"name\":\"Nona Allen\",\"time\":1718300880,\"reit\":\"5\",\"mess\":\"\",\"order_number\":\"1894259\"},{\"name\":\"Victor Miller\",\"time\":1718723100,\"reit\":\"5\",\"mess\":\"\",\"order_number\":\"36466\"},{\"name\":\"Terry Abdulaev\",\"time\":1719406200,\"reit\":\"5\",\"mess\":\"\",\"order_number\":\"LDS146445027\"},{\"name\":\"James Price\",\"time\":1719412200,\"reit\":\"5\",\"mess\":\"\",\"order_number\":\"1894259\"},{\"name\":\"James Price\",\"time\":1719412500,\"reit\":\"5\",\"mess\":\"\",\"order_number\":\"1797528\"},{\"name\":\"Tracking \",\"time\":1719429780,\"reit\":\"5\",\"mess\":\"\",\"order_number\":\"36674\"},{\"name\":\"Nona Allen\",\"time\":1720180680,\"reit\":\"5\",\"mess\":\" patience  good communication and always on time \",\"order_number\":\"12383\"},{\"name\":\"Fred Thomas\",\"time\":1720546260,\"reit\":\"5\",\"mess\":\"\",\"order_number\":\"11211761\"},{\"name\":\"Nona Allen\",\"time\":1720716480,\"reit\":\"5\",\"mess\":\"\",\"order_number\":\"119558020\"},{\"name\":\"Vlad Allen\",\"time\":1720748520,\"reit\":\"5\",\"mess\":\"\",\"order_number\":\"119497791\"},{\"name\":\"Vlad Allen\",\"time\":1720748580,\"reit\":\"5\",\"mess\":\"\",\"order_number\":\"12383\"},{\"name\":\"Vlad Allen\",\"time\":1720749480,\"reit\":\"5\",\"mess\":\"\",\"order_number\":\"119417917\"},{\"name\":\"Vlad Allen\",\"time\":1720750980,\"reit\":\"5\",\"mess\":\"\",\"order_number\":\"4326326\"},{\"name\":\"Vlad Allen\",\"time\":1720751340,\"reit\":\"5\",\"mess\":\"\",\"order_number\":\"119262433\"},{\"name\":\"Tracking \",\"time\":1720757700,\"reit\":\"5\",\"mess\":\"\",\"order_number\":\"119565617\"},{\"name\":\"Victor Miller\",\"time\":1721234640,\"reit\":\"5\",\"mess\":\"\",\"order_number\":\"109788\"},{\"name\":\"Tracking \",\"time\":1721235660,\"reit\":\"5\",\"mess\":\"\",\"order_number\":\"109788\"},{\"name\":\"Jessie Zalewski\",\"time\":1721834700,\"reit\":\"5\",\"mess\":\"\",\"order_number\":\"7413341\"},{\"name\":\"Nona Allen\",\"time\":1721923260,\"reit\":\"5\",\"mess\":\"\",\"order_number\":\"8388167\"},{\"name\":\"Victor Miller\",\"time\":1721923740,\"reit\":\"5\",\"mess\":\"\",\"order_number\":\"36880 \"},{\"name\":\"Rob Farion\",\"time\":1722462840,\"reit\":\"5\",\"mess\":\"\",\"order_number\":\"0111577\"},{\"name\":\"Victor Miller\",\"time\":1723823940,\"reit\":\"5\",\"mess\":\"\",\"order_number\":\"37758 \"},{\"name\":\"Victor Miller\",\"time\":1724168880,\"reit\":\"5\",\"mess\":\"\",\"order_number\":\"37857\"},{\"name\":\"Tracking \",\"time\":1724425380,\"reit\":\"5\",\"mess\":\"\",\"order_number\":\"37993\"},{\"name\":\"Victor Miller\",\"time\":1724425680,\"reit\":\"5\",\"mess\":\"\",\"order_number\":\"37993\"},{\"name\":\"Paul Vinikourov\",\"time\":1724960940,\"reit\":\"5\",\"mess\":\"Good rate RTG good ETA good timing good updates and communication\",\"order_number\":\"7885003\"},{\"name\":\"John Ali\",\"time\":1725024420,\"reit\":\"5\",\"mess\":\"Great Service \",\"order_number\":\" 4946\"},{\"name\":\"Victor Miller\",\"time\":1725031080,\"reit\":\"5\",\"mess\":\"\",\"order_number\":\"38204\"},{\"name\":\"Victor Miller\",\"time\":1725889380,\"reit\":\"5\",\"mess\":\"\",\"order_number\":\"81258\"},{\"name\":\"Victor Miller\",\"time\":1726061640,\"reit\":\"5\",\"mess\":\"\",\"order_number\":\"38445\"},{\"name\":\"Victor Miller\",\"time\":1726846500,\"reit\":\"5\",\"mess\":\"\",\"order_number\":\"38820\"},{\"name\":\"Victor Miller\",\"time\":1728052980,\"reit\":\"5\",\"mess\":\"\",\"order_number\":\"39330\"},{\"name\":\"Nona Allen\",\"time\":1728397440,\"reit\":\"5\",\"mess\":\"\",\"order_number\":\"7981242\"},{\"name\":\"Jessie Zalewski\",\"time\":1728658440,\"reit\":\"5\",\"mess\":\"\",\"order_number\":\"18906\"},{\"name\":\"Tracking \",\"time\":1729870020,\"reit\":\"5\",\"mess\":\"\",\"order_number\":\"39972\"},{\"name\":\"Ben Silver\",\"time\":1730382480,\"reit\":\"5\",\"mess\":\"\",\"order_number\":\"7981242\"},{\"name\":\"Victor Miller\",\"time\":1730729460,\"reit\":\"5\",\"mess\":\"\",\"order_number\":\"81696\"},{\"name\":\"Fred Thomas\",\"time\":1731681060,\"reit\":\"5\",\"mess\":\"\",\"order_number\":\"1611291\"},{\"name\":\"Paul Vinikourov\",\"time\":1731935580,\"reit\":\"5\",\"mess\":\"Good rate RTG good timing good communication good updates\",\"order_number\":\"2081673\"},{\"name\":\"Eric Mayson\",\"time\":1732895520,\"reit\":\"5\",\"mess\":\"\",\"order_number\":\"17949\"},{\"name\":\"Jacob Kowalski\",\"time\":1733342220,\"reit\":\"5\",\"mess\":\"\",\"order_number\":\"31466-06491\"},{\"name\":\"Jacob Kowalski\",\"time\":1733342280,\"reit\":\"5\",\"mess\":\"\",\"order_number\":\"319996\"},{\"name\":\"Victor Miller\",\"time\":1734107160,\"reit\":\"5\",\"mess\":\"\",\"order_number\":\"41243\"},{\"name\":\"Victor Miller\",\"time\":1735315080,\"reit\":\"5\",\"mess\":\"\",\"order_number\":\"41553 \"},{\"name\":\"Nona Allen\",\"time\":1735576920,\"reit\":\"5\",\"mess\":\"\",\"order_number\":\"2136308\"},{\"name\":\"Victor Miller\",\"time\":1735660020,\"reit\":\"5\",\"mess\":\"\",\"order_number\":\"41612\"},{\"name\":\"Victor Miller\",\"time\":1736531100,\"reit\":\"5\",\"mess\":\"\",\"order_number\":\"41783\"},{\"name\":\"Dan Vilkovsky\",\"time\":1736533560,\"reit\":\"5\",\"mess\":\"\",\"order_number\":\"31495923\"},{\"name\":\"Phill Braude\",\"time\":1737386340,\"reit\":\"5\",\"mess\":\"\",\"order_number\":\"88905\"}]",
            "warning": false,
            "dot": true,
            "dot_number": "4092999 - Active",
            "mc_number": "1559650 - Active",
            "checked_from_brokersnapshot": "1749392224",
            "check_mcdot_manual": true
        }
    },
    {
        "ID": 1758,
        "fields": {
            "driver": {
                "status": {
                    "value": "expired_documents",
                    "label": "Expired documents"
                },
                "date": "05\/02\/2025 8:00 am",
                "availability": "El Paso County_Texas, TX",
                "top_driver": false,
                "paid": false,
                "owner_driver": "Juan Gutierrez",
                "owner_phone": "(862) 391-0417",
                "owner_home_city": "Elmhurst",
                "owner_email": "jpgq970124@gmail.com",
                "owner_home": "New York, NY",
                "type": "Cargo van",
                "lwh": "145\/55\/70",
                "payload_max": "3000",
                "city": "El Paso",
                "comments": ".",
                "vin_code": "3C6MRVHG2ME514524",
                "residentship": "USA Passport",
                "driver_name": "Juan Gutierrez",
                "driver_phone": "(862) 391-0417",
                "driver_email": "jpgq970124@gmail.com",
                "driver2_name": "-",
                "driver2_phone": "",
                "driver2_email": "-",
                "main_contact": "(862) 391-0417",
                "driver_license": "520 226 301",
                "ein": "99-0867460",
                "company_name": "BLOAN CARGO LLC",
                "vehicle_year": "2021",
                "date_hr": "02\/05\/2024 6:25 pm",
                "id_hr": 113,
                "source_hr": "indeed",
                "nationality": "Colombia",
                "google_drive": true,
                "emergency_contact": "Miguel Gutierrez",
                "emergency_phone": "(862) 391-0422",
                "select_labels": [
                    "ppe",
                    "canada",
                    "real_id",
                    "macropoint",
                    "tucker-tools"
                ],
                "select_labels_distance": [
                    "any"
                ],
                "preferred_language_icon": "en"
            },
            "latitude": "31.902442",
            "longitude": "-106.413245",
            "updated_zipcode": "05\/01\/2025 3:10 pm",
            "zipcode": "79924 ",
            "last_update": "Last update: Polly Bronska - 05\/01\/2025 9:11 am",
            "date_timecode": "1746172800",
            "timecode": "1746112249",
            "driver_rating": "[{\"name\":\"Eric Mayson\",\"time\":1708975200,\"reit\":\"5\",\"mess\":\"\",\"order_number\":\"117947020\"},{\"name\":\"John Ali\",\"time\":1712951820,\"reit\":\"5\",\"mess\":\"Great service \",\"order_number\":\"54859\"},{\"name\":\"Eric Mayson\",\"time\":1715092680,\"reit\":\"2\",\"mess\":\"He can t read dispatch messages. Make sure that you discussed with him everything before book a load \",\"order_number\":\"118866467\"},{\"name\":\"Mark Adams\",\"time\":1718210040,\"reit\":\"5\",\"mess\":\"\",\"order_number\":\"2218127\"},{\"name\":\"Eric Mayson\",\"time\":1719846960,\"reit\":\"5\",\"mess\":\"\",\"order_number\":\"0449371  \"},{\"name\":\"Eric Mayson\",\"time\":1719846960,\"reit\":\"5\",\"mess\":\"\",\"order_number\":\"1726\"},{\"name\":\"Terry Abdulaev\",\"time\":1721305740,\"reit\":\"5\",\"mess\":\"\",\"order_number\":\"1758\"},{\"name\":\"Rob Farion\",\"time\":1721853720,\"reit\":\"5\",\"mess\":\"Good communication  was following all instructions that I provided to him to find shipper \",\"order_number\":\"7417\"},{\"name\":\"Terry Abdulaev\",\"time\":1722463440,\"reit\":\"5\",\"mess\":\"\",\"order_number\":\"0356701\"},{\"name\":\"Paul Vinikourov\",\"time\":1727435040,\"reit\":\"5\",\"mess\":\"Good rate RTG good communication\",\"order_number\":\"609652\"},{\"name\":\"Eric Mayson\",\"time\":1727696340,\"reit\":\"5\",\"mess\":\"\",\"order_number\":\"1408646\"},{\"name\":\"Eric Mayson\",\"time\":1727699100,\"reit\":\"5\",\"mess\":\"\",\"order_number\":\"1391695\"}]",
            "warning": false,
            "clean_background": false,
            "clean_check_date": "1714650858",
            "dot": false,
            "dot_number": "4184759 - Inactive",
            "mc_number": "1611783 - Inactive",
            "checked_from_brokersnapshot": "1749393847",
            "check_mcdot_manual": true
        }
    },
    {
        "ID": 1745,
        "fields": {
            "driver": {
                "status": {
                    "value": "loaded_enroute",
                    "label": "Loaded & Enroute"
                },
                "date": "06\/10\/2025 12:00 pm",
                "availability": "Holmes County_Ohio, OH",
                "top_driver": false,
                "paid": true,
                "owner_driver": "Umut Sozeri",
                "owner_phone": "(818) 423-0535",
                "owner_home_city": "Dayton",
                "owner_email": "umutone@hotmail.com",
                "owner_home": "Ohio, OH",
                "type": "Sprinter van",
                "lwh": "144\/52\/72",
                "payload_max": "3000",
                "city": "Millersburg",
                "comments": "Hazmat certificate ",
                "vin_code": "W1Y4NDHY2RT163048",
                "residentship": "Passport",
                "driver_name": "Umut Sozeri",
                "driver_phone": "(818) 423-0535",
                "driver_email": "umutone@hotmail.com",
                "driver2_name": "-",
                "driver2_phone": "",
                "driver2_email": "-",
                "main_contact": "(818) 423-0535",
                "driver_license": "Y1915470",
                "ein": "SSN",
                "company_name": "Individual",
                "vehicle_year": "2024",
                "date_hr": "01\/31\/2024 5:40 pm",
                "id_hr": 113,
                "source_hr": "indeed",
                "nationality": "Turkey",
                "google_drive": true,
                "emergency_contact": "jennie mixco pinto",
                "emergency_phone": "(664) 573-6818",
                "select_labels": [
                    "cdl",
                    "hazmat",
                    "ppe",
                    "real_id",
                    "macropoint",
                    "tucker-tools"
                ],
                "select_labels_distance": [
                    "any"
                ],
                "preferred_language_icon": "en"
            },
            "latitude": "40.554223",
            "longitude": "-81.915121",
            "updated_zipcode": "06\/09\/2025 3:21 pm",
            "zipcode": "Millersburg, OH 44654",
            "timecode": "1749482503",
            "last_update": "Last update: Jasmine Azhar - 06\/09\/2025 7:21 am",
            "date_timecode": "1749556800",
            "driver_rating": "[{\"name\":\"John Ali\",\"time\":1708729620,\"reit\":\"5\",\"mess\":\"Friendly \",\"order_number\":\"22414\"},{\"name\":\"Eric Mayson\",\"time\":1708974780,\"reit\":\"5\",\"mess\":\"\",\"order_number\":\"101149\"},{\"name\":\"Ben Silver\",\"time\":1711724100,\"reit\":\"5\",\"mess\":\"\",\"order_number\":\"OR249095\"},{\"name\":\"Tracking \",\"time\":1716406560,\"reit\":\"5\",\"mess\":\"\",\"order_number\":\"35830\"},{\"name\":\"Mark Adams\",\"time\":1717100820,\"reit\":\"5\",\"mess\":\"\",\"order_number\":\"4163917\"},{\"name\":\"Vlad Allen\",\"time\":1717110600,\"reit\":\"5\",\"mess\":\"\",\"order_number\":\"379162 \"},{\"name\":\"Vlad Allen\",\"time\":1717110600,\"reit\":\"5\",\"mess\":\"\",\"order_number\":\"4252442 \"},{\"name\":\"Mark Adams\",\"time\":1718977980,\"reit\":\"5\",\"mess\":\"\",\"order_number\":\"4902-6334\"},{\"name\":\"Henry Clark\",\"time\":1725397320,\"reit\":\"5\",\"mess\":\"\",\"order_number\":\"230337\"},{\"name\":\"Eric Mayson\",\"time\":1727696520,\"reit\":\"5\",\"mess\":\"\",\"order_number\":\"16704 \"},{\"name\":\"Paul Vinikourov\",\"time\":1737987240,\"reit\":\"5\",\"mess\":\"Good rate RTG good communication good service extremely patient waited for 23 hours at the airport for the freight didnt complain at all drove 2000 miles at 2 days\",\"order_number\":\"2210910\"},{\"name\":\"James Price\",\"time\":1745615220,\"reit\":\"5\",\"mess\":\"\",\"order_number\":\"8427236\"},{\"name\":\"Nona Allen\",\"time\":1749477540,\"reit\":\"5\",\"mess\":\"\",\"order_number\":\"63551\"}]",
            "warning": false,
            "dot": false,
            "checked_from_brokersnapshot": "1749394887",
            "check_mcdot_manual": false,
            "clean_background": true,
            "clean_check_date": "1739555778"
        }
    },
    {
        "ID": 1737,
        "fields": {
            "driver": {
                "status": {
                    "value": "available",
                    "label": "Available"
                },
                "date": "06\/09\/2025 9:00 am",
                "availability": "City of St. Louis_Missouri, MO",
                "top_driver": false,
                "paid": true,
                "owner_driver": "Allie Fofano",
                "owner_phone": "(267) 237-2913",
                "owner_home_city": "Harrisburg",
                "owner_email": "Fofanahali9@gmail.com",
                "owner_home": "Pennsylvania, PA",
                "type": "Cargo van",
                "lwh": "160\/50\/70",
                "payload_max": "3000",
                "city": "St. Louis",
                "comments": ".",
                "vin_code": "1FTYR3XM7KKA41221",
                "residentship": "USA Passport",
                "driver_name": "Allie Fofano",
                "driver_phone": "(267) 237-2913",
                "driver_email": "Fofanahali9@gmail.com",
                "driver2_name": "",
                "driver2_phone": "",
                "driver2_email": "",
                "main_contact": "(267) 237-2913",
                "driver_license": "28572227",
                "ein": "8 5 - 2 1 9 3 7 1 5",
                "company_name": "Fofana Rideshare LLC",
                "vehicle_year": "2019",
                "date_hr": "01\/26\/2024 9:43 pm",
                "id_hr": 94,
                "source_hr": "betterteam",
                "nationality": "American",
                "google_drive": true,
                "emergency_contact": "Fatoumata dieye",
                "emergency_phone": "(267) 250-1596",
                "select_labels": [
                    "hazmat",
                    "tsa",
                    "twic",
                    "ppe",
                    "real_id",
                    "macropoint",
                    "tucker-tools"
                ],
                "select_labels_distance": [
                    "any"
                ],
                "preferred_language_icon": "en"
            },
            "latitude": "38.644804",
            "longitude": "-90.253417",
            "updated_zipcode": "06\/09\/2025 1:04 pm",
            "zipcode": "63108",
            "last_update": "Last update: Leila Azhar - 06\/09\/2025 3:42 am",
            "date_timecode": "1749459600",
            "timecode": "1749474251",
            "driver_rating": "[{\"name\":\"Tracking \",\"time\":1709064660,\"reit\":\"5\",\"mess\":\"\",\"order_number\":\"118216385\"},{\"name\":\"Tracking \",\"time\":1709820420,\"reit\":\"5\",\"mess\":\"\",\"order_number\":\"149056\"},{\"name\":\"Victor Miller\",\"time\":1711463040,\"reit\":\"5\",\"mess\":\"\",\"order_number\":\"149056\"},{\"name\":\"Mark Adams\",\"time\":1711465200,\"reit\":\"5\",\"mess\":\"\",\"order_number\":\"4143677\"},{\"name\":\"Ben Silver\",\"time\":1714479180,\"reit\":\"5\",\"mess\":\"\",\"order_number\":\"A-11627\"},{\"name\":\"Henry Clark\",\"time\":1714740660,\"reit\":\"5\",\"mess\":\"\",\"order_number\":\"1144626\"},{\"name\":\"Jacob Kowalski\",\"time\":1717189500,\"reit\":\"5\",\"mess\":\"\",\"order_number\":\"1685626\"},{\"name\":\"John Ali\",\"time\":1719432780,\"reit\":\"5\",\"mess\":\"Good service \",\"order_number\":\"1774509\"},{\"name\":\"Jessie Zalewski\",\"time\":1724169360,\"reit\":\"3\",\"mess\":\"Providing fake ETA39s\",\"order_number\":\"8266543\"},{\"name\":\"Phill Braude\",\"time\":1725062760,\"reit\":\"5\",\"mess\":\"Good driver\",\"order_number\":\"1692745\"},{\"name\":\"Sasha Dohonov\",\"time\":1729617660,\"reit\":\"5\",\"mess\":\"\",\"order_number\":\"4584273\"},{\"name\":\"Eric Mayson\",\"time\":1730405100,\"reit\":\"5\",\"mess\":\"\",\"order_number\":\"1415827 \"},{\"name\":\"Henry Clark\",\"time\":1732298940,\"reit\":\"5\",\"mess\":\"\",\"order_number\":\"1175188\"},{\"name\":\"Paul Vinikourov\",\"time\":1736458140,\"reit\":\"5\",\"mess\":\"Good rate RTG good timing good updates\",\"order_number\":\"1220781\"},{\"name\":\"Dan Vilkovsky\",\"time\":1736533560,\"reit\":\"5\",\"mess\":\"\",\"order_number\":\"332554\"},{\"name\":\"Paul Vinikourov\",\"time\":1736894520,\"reit\":\"5\",\"mess\":\"Good rate RTG good timing good communication good updates\",\"order_number\":\"DDL-61862\"},{\"name\":\"Mark Adams\",\"time\":1737487920,\"reit\":\"5\",\"mess\":\"\",\"order_number\":\"0552199\"},{\"name\":\"Paul Vinikourov\",\"time\":1738243200,\"reit\":\"5\",\"mess\":\"Good rate RTG good timing good updates patient driver\",\"order_number\":\"8275412\"},{\"name\":\"Victor Miller\",\"time\":1738373940,\"reit\":\"5\",\"mess\":\"\",\"order_number\":\"6878497\"},{\"name\":\"Paul Vinikourov\",\"time\":1739534700,\"reit\":\"5\",\"mess\":\"Good rate RTG good timing good communication good updates\",\"order_number\":\"13927\"},{\"name\":\"Mark Adams\",\"time\":1740753600,\"reit\":\"5\",\"mess\":\"\",\"order_number\":\"0387162\"},{\"name\":\"Dan Vilkovsky\",\"time\":1743191820,\"reit\":\"3\",\"mess\":\"Canceled the load because I told him he should be waiting 1 hour at the drop off. \",\"order_number\":\"9496366\"},{\"name\":\"James Price\",\"time\":1745615280,\"reit\":\"5\",\"mess\":\"\",\"order_number\":\"0042041\"},{\"name\":\"James Price\",\"time\":1745615640,\"reit\":\"5\",\"mess\":\"\",\"order_number\":\"0042699\"},{\"name\":\"Paul Vinikourov\",\"time\":1747427700,\"reit\":\"5\",\"mess\":\"Good rate RTG good timing good communication good updates\",\"order_number\":\"8529746\"},{\"name\":\"Victor Miller\",\"time\":1748971920,\"reit\":\"5\",\"mess\":\"easy local run \",\"order_number\":\"83477\"},{\"name\":\"Victor Miller\",\"time\":1748995920,\"reit\":\"5\",\"mess\":\"\",\"order_number\":\"83484\"}]",
            "clean_background": false,
            "clean_check_date": "1743682117",
            "checked_from_brokersnapshot": "1749395488",
            "check_mcdot_manual": false,
            "warning": false,
            "dot": false
        }
    },
    {
        "ID": 1735,
        "fields": {
            "driver": {
                "status": {
                    "value": "expired_documents",
                    "label": "Expired documents"
                },
                "date": "04\/01\/2025 8:00 am",
                "availability": "Greenville County_South Carolina, SC",
                "top_driver": false,
                "paid": false,
                "owner_driver": "Joel Dingamnayal",
                "owner_phone": "(608) 745-2673",
                "owner_home_city": "Baraboo",
                "owner_email": "joeldingamnayal@gmail.com",
                "owner_home": "Wisconsin, WI",
                "type": "Cargo van",
                "lwh": "149\/53\/70",
                "payload_max": "4000",
                "city": "Greenville County",
                "comments": "JD: My car broken down I want to get that fix before renew my insurance. \r\n",
                "vin_code": "1FTBW3XG8KKA52673",
                "residentship": "Us citizen",
                "driver_name": "Joel Dingamnayal",
                "driver_phone": "(608) 745-2673",
                "driver_email": "joeldingamnayal@gmail.com",
                "driver2_name": "",
                "driver2_phone": "",
                "driver2_email": "",
                "main_contact": "(608) 745-2673",
                "driver_license": "D5254209139104",
                "ein": "",
                "company_name": "",
                "vehicle_year": "2019",
                "date_hr": "01\/26\/2024 8:01 pm",
                "id_hr": 94,
                "source_hr": "betterteam",
                "nationality": "American",
                "google_drive": true,
                "emergency_contact": "LEVI DINGAMNAYAL",
                "emergency_phone": "(520) 255-4614",
                "select_labels": [
                    "ppe",
                    "real_id",
                    "macropoint",
                    "tucker-tools"
                ],
                "select_labels_distance": [
                    "any"
                ],
                "preferred_language_icon": "en"
            },
            "latitude": "34.638704",
            "longitude": "-82.412542",
            "updated_zipcode": "03\/04\/2025 3:00 pm",
            "zipcode": "29669",
            "last_update": "Last update: Polly Bronska - 04\/04\/2025 5:26 am",
            "date_timecode": "1743494400",
            "timecode": "1741100458",
            "clean_background": true,
            "clean_check_date": "1723493126",
            "driver_rating": "[{\"name\":\"Eric Mayson\",\"time\":1706883240,\"reit\":\"1\",\"mess\":\"Gave rate and no response after that. I had to find a recovery \",\"order_number\":\"117850831 \"},{\"name\":\"Henry Clark\",\"time\":1708446960,\"reit\":\"5\",\"mess\":\"\",\"order_number\":\"225703\"},{\"name\":\"Victor Miller\",\"time\":1708529040,\"reit\":\"3\",\"mess\":\"had a PU windown for 11am12pm. Arrived at 1155. \",\"order_number\":\"105903\"},{\"name\":\"Victor Miller\",\"time\":1709906940,\"reit\":\"5\",\"mess\":\"\",\"order_number\":\"1808141\"},{\"name\":\"John Ali\",\"time\":1711467720,\"reit\":\"5\",\"mess\":\"Excellent service  Good rate \",\"order_number\":\"1810084\"},{\"name\":\"John Ali\",\"time\":1711467900,\"reit\":\"5\",\"mess\":\"Excellet service \",\"order_number\":\"3323 \"},{\"name\":\"Jacob Kowalski\",\"time\":1711712820,\"reit\":\"5\",\"mess\":\"\",\"order_number\":\"0190033\"},{\"name\":\"Vlad Allen\",\"time\":1711717560,\"reit\":\"5\",\"mess\":\"Good rate.\",\"order_number\":\"OGRE30028489\"},{\"name\":\"Ben Silver\",\"time\":1711723620,\"reit\":\"5\",\"mess\":\"\",\"order_number\":\"OR254761\"},{\"name\":\"Ben Silver\",\"time\":1711723680,\"reit\":\"5\",\"mess\":\"\",\"order_number\":\"302981\"},{\"name\":\"Victor Miller\",\"time\":1711985940,\"reit\":\"5\",\"mess\":\"\",\"order_number\":\"106814 \"},{\"name\":\"Tracking \",\"time\":1712765160,\"reit\":\"5\",\"mess\":\"\",\"order_number\":\"OR257302\"},{\"name\":\"Henry Clark\",\"time\":1713362940,\"reit\":\"5\",\"mess\":\"\",\"order_number\":\"1143422\"},{\"name\":\"Ben Silver\",\"time\":1714479540,\"reit\":\"5\",\"mess\":\"\",\"order_number\":\"OR257302\"},{\"name\":\"Jacob Kowalski\",\"time\":1714585380,\"reit\":\"5\",\"mess\":\"\",\"order_number\":\"80916\"},{\"name\":\"Travis McMillan\",\"time\":1714651380,\"reit\":\"4\",\"mess\":\"No communication at all. Good rate. Awesome timing\",\"order_number\":\" 117854\"},{\"name\":\"Victor Miller\",\"time\":1716557280,\"reit\":\"5\",\"mess\":\"\",\"order_number\":\"23911\"},{\"name\":\"Jacob Kowalski\",\"time\":1717189980,\"reit\":\"5\",\"mess\":\"\",\"order_number\":\"S2313955\"},{\"name\":\"Victor Miller\",\"time\":1718194380,\"reit\":\"5\",\"mess\":\"\",\"order_number\":\"4317503\"},{\"name\":\"Mark Adams\",\"time\":1718977680,\"reit\":\"5\",\"mess\":\"\",\"order_number\":\"268890\"},{\"name\":\"Ben Silver\",\"time\":1719407760,\"reit\":\"5\",\"mess\":\"\",\"order_number\":\"15164699\"},{\"name\":\"Victor Miller\",\"time\":1719413460,\"reit\":\"5\",\"mess\":\"\",\"order_number\":\"4299835\"},{\"name\":\"Mark Adams\",\"time\":1719579540,\"reit\":\"5\",\"mess\":\"\",\"order_number\":\"269383\"},{\"name\":\"Eric Mayson\",\"time\":1719845940,\"reit\":\"5\",\"mess\":\"\",\"order_number\":\"119204959\"},{\"name\":\"Mark Adams\",\"time\":1720439040,\"reit\":\"5\",\"mess\":\"\",\"order_number\":\"4366634\"},{\"name\":\"Victor Miller\",\"time\":1720537620,\"reit\":\"5\",\"mess\":\"\",\"order_number\":\"150334\"},{\"name\":\"Mark Adams\",\"time\":1720730340,\"reit\":\"4\",\"mess\":\"\",\"order_number\":\"0359704\"},{\"name\":\"Ben Silver\",\"time\":1721250600,\"reit\":\"5\",\"mess\":\"\",\"order_number\":\"15164699\"},{\"name\":\"Dan Vilkovsky\",\"time\":1721338440,\"reit\":\"5\",\"mess\":\"\",\"order_number\":\"1055688\"},{\"name\":\"Phill Braude\",\"time\":1723136460,\"reit\":\"5\",\"mess\":\"Great driver  good rate no issues  was ready to help unload for 50 extra\",\"order_number\":\"91776\"},{\"name\":\"Victor Miller\",\"time\":1723575600,\"reit\":\"5\",\"mess\":\"\",\"order_number\":\"9371585\"},{\"name\":\"Tracking \",\"time\":1724242320,\"reit\":\"5\",\"mess\":\"\",\"order_number\":\"1183047\"},{\"name\":\"Victor Miller\",\"time\":1724256300,\"reit\":\"5\",\"mess\":\"\",\"order_number\":\"1183047\"},{\"name\":\"Jacob Kowalski\",\"time\":1724787960,\"reit\":\"5\",\"mess\":\"\",\"order_number\":\"S2488213\"},{\"name\":\"Ben Silver\",\"time\":1724790900,\"reit\":\"5\",\"mess\":\"\",\"order_number\":\"A-15926\"},{\"name\":\"Mark Adams\",\"time\":1725058020,\"reit\":\"5\",\"mess\":\"\",\"order_number\":\"4452182\"},{\"name\":\"Mark Adams\",\"time\":1725058860,\"reit\":\"5\",\"mess\":\"\",\"order_number\":\"4489798\"},{\"name\":\"Tracking \",\"time\":1725542460,\"reit\":\"4\",\"mess\":\"\",\"order_number\":\"4499055 \"},{\"name\":\"Travis McMillan\",\"time\":1727641620,\"reit\":\"5\",\"mess\":\"\",\"order_number\":\"1986857\"},{\"name\":\"Mark Adams\",\"time\":1727704920,\"reit\":\"5\",\"mess\":\"\",\"order_number\":\"C106366\"},{\"name\":\"Mark Adams\",\"time\":1729888500,\"reit\":\"3\",\"mess\":\"Late on direct delivery for 3 hours \",\"order_number\":\"0531741 \"},{\"name\":\"Mark Adams\",\"time\":1729889340,\"reit\":\"4\",\"mess\":\"\",\"order_number\":\"C107959 \"},{\"name\":\"Eric Mayson\",\"time\":1730404260,\"reit\":\"5\",\"mess\":\"\",\"order_number\":\"1421123\"},{\"name\":\"Art Krasinski\",\"time\":1732628580,\"reit\":\"5\",\"mess\":\"\",\"order_number\":\"40025821\"},{\"name\":\"Eric Mayson\",\"time\":1732894740,\"reit\":\"5\",\"mess\":\"\",\"order_number\":\"17662\"},{\"name\":\"Mark Adams\",\"time\":1734971640,\"reit\":\"5\",\"mess\":\"\",\"order_number\":\"C112472\"},{\"name\":\"Mark Adams\",\"time\":1735052760,\"reit\":\"5\",\"mess\":\"\",\"order_number\":\"4712127\"},{\"name\":\"Dan Vilkovsky\",\"time\":1736533620,\"reit\":\"5\",\"mess\":\"\",\"order_number\":\"332493\"}]",
            "warning": false,
            "checked_from_brokersnapshot": "1749395605",
            "check_mcdot_manual": false,
            "dot": false
        }
    },
    {
        "ID": 1720,
        "fields": {
            "driver": {
                "status": {
                    "value": "available",
                    "label": "Available"
                },
                "date": "05\/15\/2025 8:00 am",
                "availability": "Philadelphia County_Pennsylvania, PA",
                "top_driver": false,
                "paid": false,
                "owner_driver": "Mikalai Naskou",
                "owner_phone": "(609) 350-8780",
                "owner_home_city": "Palm Coast",
                "owner_email": "kunehexpress@gmail.com",
                "owner_home": "Florida, FL",
                "type": "Sprinter van",
                "lwh": "188\/53\/72",
                "payload_max": "3400",
                "city": "Philadelphia",
                "comments": "NMRx3 - V.M.\r\nNo locals for now. \r\n\r\n\r\n",
                "vin_code": "W1Y4DDHY3MT082264",
                "residentship": "USA Passport",
                "driver_name": "Mikalai Naskou",
                "driver_phone": "(609) 350-8780",
                "driver_email": "kunehexpress@gmail.com",
                "driver2_name": "",
                "driver2_phone": "",
                "driver2_email": "",
                "main_contact": "(609) 350-8780",
                "driver_license": "N200-540-80-268-0",
                "ein": "8 4 1 9 9 0 1 1 9",
                "company_name": "Kunehexpress Inc",
                "vehicle_year": "2021",
                "date_hr": "01\/22\/2024 3:38 pm",
                "id_hr": 129,
                "source_hr": "indeed",
                "nationality": "USSR",
                "google_drive": true,
                "emergency_contact": "Diana",
                "emergency_phone": "(516) 225-4290",
                "select_labels": [
                    "hazmat",
                    "tsa",
                    "twic",
                    "ppe",
                    "canada",
                    "mexico",
                    "real_id",
                    "macropoint",
                    "tucker-tools",
                    "change-9"
                ],
                "select_labels_distance": [
                    "otr"
                ],
                "preferred_language_icon": "ru"
            },
            "latitude": "40.115569",
            "longitude": "-75.013276",
            "updated_zipcode": "05\/15\/2025 11:33 am",
            "zipcode": "19116",
            "timecode": "1747308805",
            "last_update": "Last update: Julia Donovan - 05\/15\/2025 3:33 am",
            "date_timecode": "1747296000",
            "driver_rating": "[{\"name\":\"Victor Miller\",\"time\":1707766320,\"reit\":\"5\",\"mess\":\"\",\"order_number\":\"6621907\"},{\"name\":\"Fred Thomas\",\"time\":1707766560,\"reit\":\"5\",\"mess\":\"Good communication and responsible\",\"order_number\":\"6597\"},{\"name\":\"Victor Miller\",\"time\":1709074140,\"reit\":\"5\",\"mess\":\"\",\"order_number\":\"6621907\"},{\"name\":\"Travis McMillan\",\"time\":1709244360,\"reit\":\"3\",\"mess\":\"Bad rate. Okay timing. Okay updates\",\"order_number\":\"104102\"},{\"name\":\"Victor Miller\",\"time\":1725368940,\"reit\":\"5\",\"mess\":\"\",\"order_number\":\"4871936 \"}]",
            "driver_notice_list": [
                {
                    "name": "Adam White",
                    "date": "1709581200",
                    "message": "Not market rate ",
                    "status": false
                }
            ],
            "warning": false,
            "dot": false,
            "clean_background": true,
            "clean_check_date": "1717961043",
            "checked_from_brokersnapshot": "1749395705",
            "check_mcdot_manual": false
        }
    },
    {
        "ID": 1714,
        "fields": {
            "driver": {
                "status": {
                    "value": "loaded_enroute",
                    "label": "Loaded & Enroute"
                },
                "date": "06\/10\/2025 2:00 pm",
                "availability": "City of St. Louis_Missouri, MO",
                "top_driver": false,
                "paid": true,
                "owner_driver": "Asdrubal Pimentel",
                "owner_phone": "(908) 356-9746",
                "owner_home_city": "Cedar Park",
                "owner_email": "Aacargovan@gmail.com",
                "owner_home": "Texas, TX",
                "type": "Sprinter van",
                "lwh": "167\/53\/72",
                "payload_max": "3700",
                "city": "St. Louis",
                "comments": ".",
                "vin_code": "W1Y40CHY4PT148170",
                "residentship": "Work Authorization",
                "driver_name": "Asdrubal Pimentel",
                "driver_phone": "(908) 356-9746",
                "driver_email": "Aacargovan@gmail.com",
                "driver2_name": "",
                "driver2_phone": "",
                "driver2_email": "",
                "main_contact": "(908) 356-9746",
                "driver_license": "46968429",
                "ein": "SSN",
                "company_name": "Individual",
                "vehicle_year": "2023",
                "date_hr": "01\/16\/2024 5:34 pm",
                "id_hr": 129,
                "source_hr": "indeed",
                "nationality": "American",
                "google_drive": true,
                "emergency_contact": "Arlis Olivares",
                "emergency_phone": "(908) 405-4763",
                "select_labels": [
                    "ppe",
                    "real_id",
                    "macropoint",
                    "tucker-tools",
                    "printer"
                ],
                "select_labels_distance": [
                    "any"
                ],
                "preferred_language_icon": "en"
            },
            "latitude": "38.611128",
            "longitude": "-90.214087",
            "updated_zipcode": "06\/09\/2025 3:45 am",
            "zipcode": "63104",
            "timecode": "1749483932",
            "last_update": "Last update: Mark Adams - 06\/09\/2025 7:45 am",
            "date_timecode": "1749564000",
            "driver_rating": "[{\"name\":\"Marshal Weaver\",\"time\":1709125140,\"reit\":\"5\",\"mess\":\"\",\"order_number\":\"14521000\"},{\"name\":\"Jacob Kowalski\",\"time\":1717189320,\"reit\":\"5\",\"mess\":\"\",\"order_number\":\"S2276925\"},{\"name\":\"Nona Allen\",\"time\":1717681320,\"reit\":\"5\",\"mess\":\"\",\"order_number\":\"EXP7267622 \"},{\"name\":\"Travis McMillan\",\"time\":1718661660,\"reit\":\"5\",\"mess\":\"\",\"order_number\":\"5004752\"},{\"name\":\"Jessie Zalewski\",\"time\":1719406200,\"reit\":\"5\",\"mess\":\"\",\"order_number\":\"119177059\"},{\"name\":\"Jessie Zalewski\",\"time\":1719942840,\"reit\":\"5\",\"mess\":\"\",\"order_number\":\"119177059 \"},{\"name\":\"Victor Miller\",\"time\":1721069100,\"reit\":\"5\",\"mess\":\"\",\"order_number\":\" 4384898 \"},{\"name\":\"Ben Silver\",\"time\":1725019320,\"reit\":\"5\",\"mess\":\"\",\"order_number\":\"EL3906648\"},{\"name\":\"Victor Miller\",\"time\":1725973680,\"reit\":\"5\",\"mess\":\"\",\"order_number\":\"1207207\"},{\"name\":\"Eric Mayson\",\"time\":1727698380,\"reit\":\"5\",\"mess\":\"\",\"order_number\":\"1397262\"},{\"name\":\"Victor Miller\",\"time\":1732032240,\"reit\":\"5\",\"mess\":\"\",\"order_number\":\"4669084\"},{\"name\":\"Phill Braude\",\"time\":1732729800,\"reit\":\"5\",\"mess\":\"\",\"order_number\":\"17495\"},{\"name\":\"Vlad Allen\",\"time\":1740065280,\"reit\":\"1\",\"mess\":\"Cancelled the load on me\",\"order_number\":\"000\"},{\"name\":\"Paul Vinikourov\",\"time\":1740484560,\"reit\":\"5\",\"mess\":\"Good rate RTG good timing good communication\",\"order_number\":\"651321\"},{\"name\":\"James Price\",\"time\":1743104640,\"reit\":\"4\",\"mess\":\"Was late for PU said 1hr ETA but was watching moovies and ended up being late for pick up. Delivered the load late as well. \",\"order_number\":\"1711235\"},{\"name\":\"James Price\",\"time\":1743104760,\"reit\":\"5\",\"mess\":\"Good job everything was on time. Made 1150 miles loaded and 170 empty in less than 24 hours. \",\"order_number\":\"1850495\"},{\"name\":\"Victor Miller\",\"time\":1743791820,\"reit\":\"5\",\"mess\":\"\",\"order_number\":\"153351\"},{\"name\":\"Mark Adams\",\"time\":1747754460,\"reit\":\"5\",\"mess\":\"\",\"order_number\":\"4629915\"}]",
            "warning": false,
            "checked_from_brokersnapshot": "1749397977",
            "check_mcdot_manual": false,
            "dot": false
        }
    },
    {
        "ID": 1701,
        "fields": {
            "driver": {
                "status": {
                    "value": "loaded_enroute",
                    "label": "Loaded & Enroute"
                },
                "date": "06\/10\/2025 8:00 am",
                "availability": "Bulloch County_Georgia, GA",
                "top_driver": false,
                "paid": true,
                "owner_driver": "Carlos Ferrer",
                "owner_phone": "(901) 336-1703",
                "owner_home_city": "Lakeland",
                "owner_email": "fercar11@gmail.com",
                "owner_home": "Tennessee, TN",
                "type": "Cargo van",
                "lwh": "158\/56\/69",
                "payload_max": "3500",
                "city": "Bulloch County",
                "comments": ".",
                "vin_code": "3C6MRVJG0ME551162",
                "residentship": "Green Card",
                "driver_name": "Carlos Ferrer",
                "driver_phone": "(901) 336-1703",
                "driver_email": "fercar11@gmail.com",
                "driver2_name": "-",
                "driver2_phone": "",
                "driver2_email": "-",
                "main_contact": "(901) 336-1703",
                "driver_license": "134353911",
                "ein": "SSN",
                "company_name": "Individual",
                "vehicle_year": "2021",
                "date_hr": "01\/10\/2024 4:48 pm",
                "id_hr": 113,
                "source_hr": "other",
                "nationality": "Venezuela",
                "google_drive": true,
                "emergency_contact": "Iván Díaz",
                "emergency_phone": "(786) 499-4607",
                "select_labels": [
                    "ppe",
                    "canada",
                    "macropoint",
                    "tucker-tools",
                    "printer"
                ],
                "select_labels_distance": [
                    "any"
                ],
                "preferred_language_icon": "en"
            },
            "latitude": "32.399447",
            "longitude": "-81.82894",
            "updated_zipcode": "06\/09\/2025 3:44 am",
            "zipcode": "30458",
            "last_update": "Last update: Mark Adams - 06\/09\/2025 7:44 am",
            "date_timecode": "1749542400",
            "clean_background": true,
            "clean_check_date": "1747396294",
            "timecode": "1749483853",
            "driver_rating": "[{\"name\":\"Fred Thomas\",\"time\":1712952720,\"reit\":\"5\",\"mess\":\"\",\"order_number\":\"1468815\"},{\"name\":\"Terry Abdulaev\",\"time\":1712952780,\"reit\":\"5\",\"mess\":\"\",\"order_number\":\"15420\"},{\"name\":\"Ben Silver\",\"time\":1721249340,\"reit\":\"5\",\"mess\":\"\",\"order_number\":\"61304\"},{\"name\":\"Nona Allen\",\"time\":1721310600,\"reit\":\"5\",\"mess\":\"\",\"order_number\":\"OGRE30038934\"},{\"name\":\"Ben Silver\",\"time\":1723656540,\"reit\":\"5\",\"mess\":\"\",\"order_number\":\"OR298797\"},{\"name\":\"Ben Silver\",\"time\":1724791020,\"reit\":\"5\",\"mess\":\"\",\"order_number\":\"OR298797\"},{\"name\":\"Eric Mayson\",\"time\":1727699400,\"reit\":\"5\",\"mess\":\"\",\"order_number\":\"2564037 \"},{\"name\":\"Henry Clark\",\"time\":1729200480,\"reit\":\"4\",\"mess\":\"\",\"order_number\":\"231290\"},{\"name\":\"Mark Adams\",\"time\":1729889760,\"reit\":\"5\",\"mess\":\"\",\"order_number\":\"0529692\"},{\"name\":\"Terry Abdulaev\",\"time\":1738197840,\"reit\":\"5\",\"mess\":\"\",\"order_number\":\"LDS14874913\"},{\"name\":\"Terry Abdulaev\",\"time\":1739461260,\"reit\":\"5\",\"mess\":\"\",\"order_number\":\"16267575\"},{\"name\":\"Terry Abdulaev\",\"time\":1739581380,\"reit\":\"5\",\"mess\":\"\",\"order_number\":\"16267575\"},{\"name\":\"Mark Adams\",\"time\":1740754560,\"reit\":\"5\",\"mess\":\"\",\"order_number\":\"3930291\"},{\"name\":\"Ben Silver\",\"time\":1746112980,\"reit\":\"5\",\"mess\":\"\",\"order_number\":\" 1733867\"},{\"name\":\"Mark Adams\",\"time\":1746480780,\"reit\":\"5\",\"mess\":\"\",\"order_number\":\"9490667\"}]",
            "warning": false,
            "checked_from_brokersnapshot": "1749398574",
            "check_mcdot_manual": false,
            "dot": false
        }
    },
    {
        "ID": 1698,
        "fields": {
            "driver": {
                "status": {
                    "value": "available",
                    "label": "Available"
                },
                "date": "06\/09\/2025 8:00 am",
                "availability": "Grant County_Washington, WA",
                "top_driver": false,
                "paid": true,
                "owner_driver": "Miroslav Patcherezov",
                "owner_phone": "(716) 997-5050",
                "owner_home_city": "Buffalo",
                "owner_email": "patchi772000@yahoo.com",
                "owner_home": "New York, NY",
                "type": "Sprinter van",
                "lwh": "185\/52\/70",
                "payload_max": "3700",
                "city": "Grant County",
                "comments": "FAST CARD - can cross USA - CANADA",
                "vin_code": "W1Y4NDHY8RT165967",
                "residentship": "USA Passport",
                "driver_name": "Miroslav Patcherezov",
                "driver_phone": "(716) 997-5050",
                "driver_email": "patchi772000@yahoo.com",
                "driver2_name": "",
                "driver2_phone": "",
                "driver2_email": "",
                "main_contact": "(716) 997-5050",
                "driver_license": "236333042 - Enhanced*",
                "ein": "",
                "company_name": "",
                "vehicle_year": "2024",
                "date_hr": "01\/09\/2024 6:42 pm",
                "id_hr": 94,
                "source_hr": "betterteam",
                "nationality": "Bulgarian",
                "google_drive": true,
                "emergency_contact": "Petia Patcherezova",
                "emergency_phone": "(716) 544-2874",
                "select_labels": [
                    "cdl",
                    "twic",
                    "ppe",
                    "e-track",
                    "canada",
                    "real_id",
                    "macropoint",
                    "tucker-tools"
                ],
                "select_labels_distance": [
                    "any"
                ],
                "preferred_language_icon": "en"
            },
            "latitude": "47.168643",
            "longitude": "-119.842939",
            "updated_zipcode": "06\/09\/2025 12:41 pm",
            "zipcode": "98848",
            "last_update": "Last update: Leila Azhar - 06\/09\/2025 4:41 am",
            "date_timecode": "1749456000",
            "timecode": "1749472905",
            "driver_rating": "[{\"name\":\"Fred Thomas\",\"time\":1706816220,\"reit\":\"5\",\"mess\":\"\",\"order_number\":\"27038343\"},{\"name\":\"Tracking \",\"time\":1709037000,\"reit\":\"5\",\"mess\":\"\",\"order_number\":\"1588208\"},{\"name\":\"Ben Silver\",\"time\":1711461900,\"reit\":\"5\",\"mess\":\"\",\"order_number\":\"53926\"},{\"name\":\"Ben Silver\",\"time\":1714479420,\"reit\":\"5\",\"mess\":\"\",\"order_number\":\"55190 \"},{\"name\":\"Henry Clark\",\"time\":1715879040,\"reit\":\"4\",\"mess\":\"90 miles of deadhead for 3 hours but all in timeall good\",\"order_number\":\"227986\"},{\"name\":\"Henry Clark\",\"time\":1718195340,\"reit\":\"5\",\"mess\":\"\",\"order_number\":\"228601\"},{\"name\":\"Ben Silver\",\"time\":1719407700,\"reit\":\"5\",\"mess\":\"\",\"order_number\":\"7656716\"},{\"name\":\"Jessie Zalewski\",\"time\":1719942480,\"reit\":\"5\",\"mess\":\"\",\"order_number\":\"571732\"},{\"name\":\"Ben Silver\",\"time\":1720530000,\"reit\":\"5\",\"mess\":\"\",\"order_number\":\"60572\"},{\"name\":\"Terry Abdulaev\",\"time\":1721684520,\"reit\":\"5\",\"mess\":\"\",\"order_number\":\"0356556\"},{\"name\":\"Henry Clark\",\"time\":1727123460,\"reit\":\"5\",\"mess\":\"\",\"order_number\":\"230699\"},{\"name\":\"Peter Novak\",\"time\":1735578960,\"reit\":\"5\",\"mess\":\"\",\"order_number\":\"LOAD #:3159203-1\"},{\"name\":\"Mark Adams\",\"time\":1736193600,\"reit\":\"5\",\"mess\":\"\",\"order_number\":\"4758937\"},{\"name\":\"Paul Vinikourov\",\"time\":1736457840,\"reit\":\"5\",\"mess\":\"Good rate RTG good timing good updates\",\"order_number\":\"87110\"},{\"name\":\"Victor Miller\",\"time\":1736530140,\"reit\":\"5\",\"mess\":\"Good driver\",\"order_number\":\"1196350\"},{\"name\":\"Victor Miller\",\"time\":1738094700,\"reit\":\"5\",\"mess\":\"\",\"order_number\":\"159078\"},{\"name\":\"Victor Miller\",\"time\":1738172820,\"reit\":\"5\",\"mess\":\"top rating \",\"order_number\":\"1198399\"},{\"name\":\"Ben Silver\",\"time\":1738339080,\"reit\":\"5\",\"mess\":\"\",\"order_number\":\"74441\"},{\"name\":\"Umid Bekov\",\"time\":1739395200,\"reit\":\"5\",\"mess\":\"Good rate good communication strong for long trips\",\"order_number\":\"3284451\"},{\"name\":\"Victor Miller\",\"time\":1740832860,\"reit\":\"5\",\"mess\":\"\",\"order_number\":\" 1201062\"},{\"name\":\"Terry Abdulaev\",\"time\":1743448620,\"reit\":\"5\",\"mess\":\"\",\"order_number\":\"2742019\"},{\"name\":\"Paul Vinikourov\",\"time\":1744133400,\"reit\":\"5\",\"mess\":\"Good rate RTG good timing good communication good updates\",\"order_number\":\"2893980\"},{\"name\":\"James Price\",\"time\":1745615040,\"reit\":\"5\",\"mess\":\"\",\"order_number\":\"1821490\"},{\"name\":\"Peter Novak\",\"time\":1745617080,\"reit\":\"5\",\"mess\":\"\",\"order_number\":\"4886886\"},{\"name\":\"Paul Vinikourov\",\"time\":1746702060,\"reit\":\"5\",\"mess\":\"Good rate RTG good timing good communication good updates\",\"order_number\":\"11273\"},{\"name\":\"Mark Adams\",\"time\":1747754640,\"reit\":\"5\",\"mess\":\"\",\"order_number\":\" SPT-496685\"},{\"name\":\"Victor Miller\",\"time\":1748952660,\"reit\":\"5\",\"mess\":\"\",\"order_number\":\" 1211890\"}]",
            "clean_background": true,
            "clean_check_date": "1736513117",
            "warning": false,
            "checked_from_brokersnapshot": "1749398581",
            "check_mcdot_manual": true,
            "dot": false,
            "dot_number": "1829824 - Inactive"
        }
    },
    {
        "ID": 1690,
        "fields": {
            "driver": {
                "status": {
                    "value": "available",
                    "label": "Available"
                },
                "date": "06\/07\/2025 10:00 am",
                "availability": "Miami-Dade County_Florida, FL",
                "top_driver": false,
                "paid": true,
                "owner_driver": "Sandro Pena",
                "owner_phone": "(954) 394-1858",
                "owner_home_city": "Hollywood",
                "owner_email": "SPdeadstock.llc@gmail.com",
                "owner_home": "Florida, FL",
                "type": "Cargo van",
                "lwh": "156\/52\/73",
                "payload_max": "3200",
                "city": "Miami-Dade County",
                "comments": "OA: please always clarify who is the driver, as sometimes they do not drive as a team.Two-wheel dolly \r\n\r\nmc active ",
                "vin_code": "1FTBR3XG6LKB20106",
                "residentship": "USA Passport",
                "driver_name": "Sandro Pena",
                "driver_phone": "(954) 394-1858",
                "driver_email": "SPdeadstock.llc@gmail.com",
                "driver2_name": "Sandi Molina",
                "driver2_phone": "(551) 998-9505",
                "driver2_email": "SPdeadstock.llc@gmail.com",
                "main_contact": "(954) 394-1858",
                "driver_license": "P500-780-87-288-0",
                "ein": "8 1 4 8 6 6 3 4 0",
                "company_name": "SP Deadstock LLC",
                "vehicle_year": "2020",
                "date_hr": "01\/05\/2024 9:40 pm",
                "id_hr": 129,
                "source_hr": "indeed",
                "nationality": "American",
                "google_drive": true,
                "emergency_contact": "Martha Pena",
                "emergency_phone": "(305) 343-9977",
                "select_labels": [
                    "twic",
                    "ppe",
                    "team",
                    "canada",
                    "real_id",
                    "macropoint",
                    "tucker-tools",
                    "change-9",
                    "printer"
                ],
                "select_labels_distance": [
                    "any"
                ],
                "preferred_language_icon": "en"
            },
            "latitude": "25.917733",
            "longitude": "-80.384455",
            "updated_zipcode": "06\/09\/2025 11:38 am",
            "zipcode": "33018",
            "timecode": "1749469118",
            "last_update": "Last update: Leila Azhar - 06\/09\/2025 3:38 am",
            "date_timecode": "1749290400",
            "driver_rating": "[{\"name\":\"Eric Mayson\",\"time\":1706884800,\"reit\":\"5\",\"mess\":\"\",\"order_number\":\"117632867.\"},{\"name\":\"Eric Mayson\",\"time\":1706884800,\"reit\":\"5\",\"mess\":\"\",\"order_number\":\"117672868\"},{\"name\":\"Eric Mayson\",\"time\":1706884920,\"reit\":\"5\",\"mess\":\"\",\"order_number\":\"117742574\"},{\"name\":\"Eric Mayson\",\"time\":1708974300,\"reit\":\"5\",\"mess\":\"\",\"order_number\":\"118187446\"},{\"name\":\"Vlad Allen\",\"time\":1709217660,\"reit\":\"5\",\"mess\":\"Good rate. Patient driver.\",\"order_number\":\"1782016\"},{\"name\":\"Eric Mayson\",\"time\":1711469400,\"reit\":\"5\",\"mess\":\"\",\"order_number\":\"118318835\"},{\"name\":\"Victor Miller\",\"time\":1713272880,\"reit\":\"5\",\"mess\":\"\",\"order_number\":\"1837767\"},{\"name\":\"Terry Abdulaev\",\"time\":1714500060,\"reit\":\"5\",\"mess\":\"\",\"order_number\":\"GLG7613\"},{\"name\":\"Eric Mayson\",\"time\":1714505400,\"reit\":\"5\",\"mess\":\"\",\"order_number\":\"118322098\"},{\"name\":\"Eric Mayson\",\"time\":1721762040,\"reit\":\"5\",\"mess\":\"\",\"order_number\":\"15041\"},{\"name\":\"Tracking \",\"time\":1722439500,\"reit\":\"5\",\"mess\":\"\",\"order_number\":\"15424\"},{\"name\":\"Victor Miller\",\"time\":1722620340,\"reit\":\"5\",\"mess\":\"good rate updated with ETAs. \",\"order_number\":\"150595\"},{\"name\":\"Eric Mayson\",\"time\":1724881440,\"reit\":\"5\",\"mess\":\"\",\"order_number\":\"15424\"},{\"name\":\"Victor Miller\",\"time\":1726252080,\"reit\":\"5\",\"mess\":\"\",\"order_number\":\"81317 \"},{\"name\":\"Eric Mayson\",\"time\":1727696940,\"reit\":\"5\",\"mess\":\"\",\"order_number\":\"16589\"},{\"name\":\"Eric Mayson\",\"time\":1727698080,\"reit\":\"5\",\"mess\":\"\",\"order_number\":\"SBRU0003770\"},{\"name\":\"Eric Mayson\",\"time\":1727699040,\"reit\":\"5\",\"mess\":\"\",\"order_number\":\"16061 \"},{\"name\":\"Fred Thomas\",\"time\":1728478620,\"reit\":\"5\",\"mess\":\"\",\"order_number\":\"1586960\"},{\"name\":\"Eric Mayson\",\"time\":1730403960,\"reit\":\"5\",\"mess\":\"\",\"order_number\":\"1423381\"},{\"name\":\"Victor Miller\",\"time\":1731617160,\"reit\":\"3\",\"mess\":\"didn39t mention that he has a driver. I gave his phone and broker called him for dispatch. \",\"order_number\":\"2041787\"},{\"name\":\"Tracking \",\"time\":1732039620,\"reit\":\"5\",\"mess\":\"\",\"order_number\":\"151896\"},{\"name\":\"Eric Mayson\",\"time\":1732895100,\"reit\":\"5\",\"mess\":\"\",\"order_number\":\"17779\"},{\"name\":\"Aha Kramich\",\"time\":1732897680,\"reit\":\"5\",\"mess\":\"\",\"order_number\":\"1179519\"},{\"name\":\"Paul Vinikourov\",\"time\":1733843640,\"reit\":\"5\",\"mess\":\"Good rate RTG good timing good updates good communication\",\"order_number\":\"2130716\"},{\"name\":\"Nona Allen\",\"time\":1735325160,\"reit\":\"5\",\"mess\":\"good updates and great timing\",\"order_number\":\"18729\"},{\"name\":\"Travis McMillan\",\"time\":1735577520,\"reit\":\"5\",\"mess\":\"\",\"order_number\":\"1639617\"},{\"name\":\"Eric Mayson\",\"time\":1735922940,\"reit\":\"5\",\"mess\":\"\",\"order_number\":\"18729\"},{\"name\":\"Dan Vilkovsky\",\"time\":1736533560,\"reit\":\"5\",\"mess\":\"\",\"order_number\":\"332549\"},{\"name\":\"Eric Mayson\",\"time\":1737751800,\"reit\":\"5\",\"mess\":\"\",\"order_number\":\"19176 \"},{\"name\":\"Eric Mayson\",\"time\":1737752220,\"reit\":\"5\",\"mess\":\"\",\"order_number\":\"19297\"},{\"name\":\"Eric Mayson\",\"time\":1737752400,\"reit\":\"5\",\"mess\":\"\",\"order_number\":\"19348\"},{\"name\":\"Victor Miller\",\"time\":1738178100,\"reit\":\"5\",\"mess\":\"\",\"order_number\":\"114079\"},{\"name\":\"Eric Mayson\",\"time\":1738353360,\"reit\":\"5\",\"mess\":\"\",\"order_number\":\"19414\"},{\"name\":\"Victor Miller\",\"time\":1738951860,\"reit\":\"5\",\"mess\":\"\",\"order_number\":\" 152686\"},{\"name\":\"Nona Allen\",\"time\":1739885700,\"reit\":\"5\",\"mess\":\"great job \",\"order_number\":\"442543\"},{\"name\":\"Travis McMillan\",\"time\":1740778800,\"reit\":\"5\",\"mess\":\"\",\"order_number\":\"46999\"},{\"name\":\"Victor Miller\",\"time\":1741359300,\"reit\":\"5\",\"mess\":\"\",\"order_number\":\"153022\"},{\"name\":\"Paul Vinikourov\",\"time\":1742569860,\"reit\":\"5\",\"mess\":\"Good rate RTG good timing good communication good updates\",\"order_number\":\"2329482\"},{\"name\":\"Eric Mayson\",\"time\":1743422580,\"reit\":\"5\",\"mess\":\"Has few drivers good service \",\"order_number\":\"20833\"},{\"name\":\"Eric Mayson\",\"time\":1743422880,\"reit\":\"5\",\"mess\":\"\",\"order_number\":\"20771\"},{\"name\":\"Eric Mayson\",\"time\":1743423180,\"reit\":\"5\",\"mess\":\"\",\"order_number\":\" 20567\"},{\"name\":\"Eric Mayson\",\"time\":1743424020,\"reit\":\"5\",\"mess\":\"\",\"order_number\":\"20218\"},{\"name\":\"Travis McMillan\",\"time\":1743458460,\"reit\":\"5\",\"mess\":\"\",\"order_number\":\" 2149298\"},{\"name\":\"Travis McMillan\",\"time\":1744036800,\"reit\":\"5\",\"mess\":\"\",\"order_number\":\"2006006\"},{\"name\":\"Victor Miller\",\"time\":1744904820,\"reit\":\"5\",\"mess\":\"\",\"order_number\":\"153549 \"},{\"name\":\"Paul Vinikourov\",\"time\":1745926020,\"reit\":\"5\",\"mess\":\"Good rate RTG good timing good communication good updates\",\"order_number\":\"192854\"},{\"name\":\"Victor Miller\",\"time\":1746225600,\"reit\":\"5\",\"mess\":\"\",\"order_number\":\" 8739681\"},{\"name\":\"Vlad Allen\",\"time\":1748377560,\"reit\":\"1\",\"mess\":\"Asked 100 extra for delivering load back to the shipper 15 milesGreedy driver.\",\"order_number\":\"DRWMRN11042951\"}]",
            "warning": false,
            "dot": true,
            "checked_from_brokersnapshot": "1749398706",
            "check_mcdot_manual": true,
            "clean_background": false,
            "clean_check_date": "1738240695",
            "dot_number": "4388323 - Active",
            "mc_number": "1721216 - Active"
        }
    },
    {
        "ID": 1688,
        "fields": {
            "driver": {
                "status": {
                    "value": "available",
                    "label": "Available"
                },
                "date": "06\/08\/2025 8:00 pm",
                "availability": "Bartow County_Georgia, GA",
                "top_driver": false,
                "paid": false,
                "owner_driver": "Jose Brewer",
                "owner_phone": "(248) 991-4691",
                "owner_home_city": "Highland Park",
                "owner_email": "Hwcxxv@gmail.com",
                "owner_home": "Michigan, MI",
                "type": "Cargo van",
                "lwh": "121\/55\/57",
                "payload_max": "3000",
                "city": "Bartow County",
                "comments": "",
                "vin_code": "3C6LRVAG7NE118869",
                "residentship": "USA Passport",
                "driver_name": "Jose Brewer",
                "driver_phone": "(248) 991-4691",
                "driver_email": "Hwcxxv@gmail.com",
                "driver2_name": "-",
                "driver2_phone": "",
                "driver2_email": "-",
                "main_contact": "(248) 991-4691",
                "driver_license": "B 660 440 488 067",
                "ein": "85-2799301",
                "company_name": "Handle With Care 25 LLC",
                "vehicle_year": "2022",
                "date_hr": "01\/05\/2024 8:17 pm",
                "id_hr": 113,
                "source_hr": "indeed",
                "nationality": "American",
                "google_drive": true,
                "emergency_contact": "Jai-Qwuan Brewer",
                "emergency_phone": "(313) 646-8254",
                "select_labels": [
                    "tsa",
                    "twic",
                    "ppe",
                    "canada",
                    "real_id",
                    "macropoint",
                    "tucker-tools",
                    "printer"
                ],
                "select_labels_distance": [
                    "any"
                ],
                "preferred_language_icon": "en"
            },
            "latitude": "34.167879",
            "longitude": "-84.852014",
            "updated_zipcode": "06\/09\/2025 12:14 pm",
            "zipcode": "30120",
            "last_update": "Last update: Leila Azhar - 06\/09\/2025 4:14 am",
            "date_timecode": "1749412800",
            "timecode": "1749471250",
            "clean_background": true,
            "clean_check_date": "1747312552",
            "warning": false,
            "dot": false,
            "driver_rating": "[{\"name\":\"Fred Thomas\",\"time\":1719347460,\"reit\":\"5\",\"mess\":\"\",\"order_number\":\"119410441 \"},{\"name\":\"Mark Adams\",\"time\":1719579420,\"reit\":\"4\",\"mess\":\"\",\"order_number\":\"269554\"},{\"name\":\"Mark Adams\",\"time\":1724084220,\"reit\":\"5\",\"mess\":\"\",\"order_number\":\"29485019\"},{\"name\":\"Paul Vinikourov\",\"time\":1734650280,\"reit\":\"2\",\"mess\":\"Lied about his current location late for delivery for 1 hour bad communication not able to communicate and understand what he needs to do\",\"order_number\":\"1907747\"},{\"name\":\"Terry Abdulaev\",\"time\":1737065760,\"reit\":\"2\",\"mess\":\"Provided wrong ETA changed ETA twice inpatient driver.Be careful of the ETA before sending him to any loads.\",\"order_number\":\"585162\"},{\"name\":\"Ben Silver\",\"time\":1738340640,\"reit\":\"5\",\"mess\":\"\",\"order_number\":\"16150497\"}]",
            "dot_number": "4027871 - Inactive",
            "mc_number": "1520956 - Inactive",
            "checked_from_brokersnapshot": "1749398826",
            "check_mcdot_manual": true
        }
    },
    {
        "ID": 1687,
        "fields": {
            "driver": {
                "status": {
                    "value": "on_vocation",
                    "label": "On weekend"
                },
                "date": "06\/16\/2025 11:00 am",
                "availability": "Multnomah County_Oregon, OR",
                "top_driver": false,
                "paid": false,
                "owner_driver": "Noe Gonzalez",
                "owner_phone": "(503) 575-5971",
                "owner_home_city": "Portland",
                "owner_email": "esparzanoah@yahoo.com",
                "owner_home": "Oregon, OR",
                "type": "Cargo van",
                "lwh": "143\/56\/69",
                "payload_max": "4000",
                "city": "Portland",
                "comments": ".",
                "vin_code": "3C6LRVDG5PE536300",
                "residentship": "USA Passport",
                "driver_name": "Noe Gonzalez",
                "driver_phone": "(503) 575-5971",
                "driver_email": "esparzanoah@yahoo.com",
                "driver2_name": "",
                "driver2_phone": "",
                "driver2_email": "",
                "main_contact": "(503) 575-5971",
                "driver_license": "8586028",
                "ein": "88-1411929",
                "company_name": "Alphamar Trucking LLC",
                "vehicle_year": "2023",
                "date_hr": "01\/05\/2024 8:06 pm",
                "id_hr": false,
                "source_hr": "betterteam",
                "nationality": "Mexican",
                "google_drive": true,
                "emergency_contact": "Edwin Mutul",
                "emergency_phone": "(971) 421-4078",
                "select_labels": [
                    "twic",
                    "ppe",
                    "canada",
                    "real_id",
                    "macropoint",
                    "tucker-tools"
                ],
                "select_labels_distance": [
                    "any"
                ],
                "preferred_language_icon": "en"
            },
            "latitude": "45.533467",
            "longitude": "-122.650095",
            "updated_zipcode": "06\/09\/2025 3:49 pm",
            "zipcode": "97220 Portland OR",
            "timecode": "1749484177",
            "last_update": "Last update: Leila Azhar - 06\/09\/2025 7:49 am",
            "date_timecode": "1750071600",
            "driver_rating": "[{\"name\":\"John Ali\",\"time\":1708730100,\"reit\":\"4\",\"mess\":\"Mediocre\",\"order_number\":\" 19625\"},{\"name\":\"Travis McMillan\",\"time\":1709202420,\"reit\":\"4\",\"mess\":\"\",\"order_number\":\" 1515979\"},{\"name\":\"Mark Adams\",\"time\":1709214360,\"reit\":\"5\",\"mess\":\"\",\"order_number\":\"0307467\"},{\"name\":\"Vlad Allen\",\"time\":1709217240,\"reit\":\"4\",\"mess\":\"The driver was asking for the load back too many times.\",\"order_number\":\"31160862\"},{\"name\":\"Tracking \",\"time\":1710516180,\"reit\":\"5\",\"mess\":\"\",\"order_number\":\"EXP7244393\"},{\"name\":\"John Ali\",\"time\":1711751520,\"reit\":\"5\",\"mess\":\"Good service \",\"order_number\":\"19625\"},{\"name\":\"Henry Clark\",\"time\":1715879160,\"reit\":\"5\",\"mess\":\"Amazing rate. Great driver. All in timeUsed to wait for the load until morning and even didn39t cry\",\"order_number\":\"227967\"},{\"name\":\"Jessie Zalewski\",\"time\":1717002660,\"reit\":\"5\",\"mess\":\"Good rate and patient\",\"order_number\":\"4575058\"},{\"name\":\"John Ali\",\"time\":1717002720,\"reit\":\"5\",\"mess\":\"Excellent Service\",\"order_number\":\" 1032117\"},{\"name\":\"Vlad Allen\",\"time\":1717110300,\"reit\":\"5\",\"mess\":\"\",\"order_number\":\"31160862\"},{\"name\":\"Vlad Allen\",\"time\":1717110300,\"reit\":\"5\",\"mess\":\"\",\"order_number\":\"EXP7244393\"},{\"name\":\"Victor Miller\",\"time\":1719238500,\"reit\":\"5\",\"mess\":\"\",\"order_number\":\"36552\"},{\"name\":\"James Price\",\"time\":1719412680,\"reit\":\"5\",\"mess\":\"5 star \",\"order_number\":\"1347226\"},{\"name\":\"Jacob Kowalski\",\"time\":1720728780,\"reit\":\"5\",\"mess\":\"\",\"order_number\":\"95869\"},{\"name\":\"Jacob Kowalski\",\"time\":1721921820,\"reit\":\"5\",\"mess\":\"\",\"order_number\":\"96109\"},{\"name\":\"John Ali\",\"time\":1722946080,\"reit\":\"5\",\"mess\":\"Highly Professional Driver Good Rates\",\"order_number\":\"6033868\"},{\"name\":\"Nona Allen\",\"time\":1724437080,\"reit\":\"5\",\"mess\":\"everything on time\",\"order_number\":\"2546034\"},{\"name\":\"James Price\",\"time\":1727386980,\"reit\":\"5\",\"mess\":\"\",\"order_number\":\"1976320\"},{\"name\":\"Mark Adams\",\"time\":1727704860,\"reit\":\"5\",\"mess\":\"\",\"order_number\":\"0368182\"},{\"name\":\"Nona Allen\",\"time\":1728397980,\"reit\":\"5\",\"mess\":\"\",\"order_number\":\"120525514\"},{\"name\":\"Victor Miller\",\"time\":1728993960,\"reit\":\"4\",\"mess\":\"\",\"order_number\":\"39557\"},{\"name\":\"Henry Clark\",\"time\":1729200240,\"reit\":\"5\",\"mess\":\"\",\"order_number\":\"16858\"},{\"name\":\"Eshan Sah\",\"time\":1729633560,\"reit\":\"5\",\"mess\":\"Really good for Canada loads\",\"order_number\":\"184326\"},{\"name\":\"Jacob Kowalski\",\"time\":1730670240,\"reit\":\"5\",\"mess\":\"\",\"order_number\":\"S2608357\"},{\"name\":\"Terry Abdulaev\",\"time\":1734473400,\"reit\":\"5\",\"mess\":\"\",\"order_number\":\"1776001\"},{\"name\":\"James Price\",\"time\":1735311960,\"reit\":\"5\",\"mess\":\"\",\"order_number\":\"2156376\"},{\"name\":\"James Price\",\"time\":1735312080,\"reit\":\"5\",\"mess\":\"\",\"order_number\":\"2152634\"},{\"name\":\"Ben Silver\",\"time\":1735582860,\"reit\":\"5\",\"mess\":\"\",\"order_number\":\"OR337708\"},{\"name\":\"Victor Miller\",\"time\":1736444100,\"reit\":\"5\",\"mess\":\"\",\"order_number\":\"41761\"},{\"name\":\"Mark Adams\",\"time\":1737488100,\"reit\":\"5\",\"mess\":\"\",\"order_number\":\"2458625\"},{\"name\":\"Terry Abdulaev\",\"time\":1740789600,\"reit\":\"5\",\"mess\":\"\",\"order_number\":\"LDS14897009\"},{\"name\":\"Victor Miller\",\"time\":1742926920,\"reit\":\"5\",\"mess\":\"\",\"order_number\":\" 2163378\"},{\"name\":\"James Price\",\"time\":1745615340,\"reit\":\"5\",\"mess\":\"\",\"order_number\":\"1824664\"}]",
            "clean_background": true,
            "clean_check_date": "1715276909",
            "warning": false,
            "checked_from_brokersnapshot": "1749398970",
            "check_mcdot_manual": false,
            "dot": false
        }
    },
    {
        "ID": 1685,
        "fields": {
            "driver": {
                "status": {
                    "value": "available",
                    "label": "Available"
                },
                "date": "06\/08\/2025 8:00 am",
                "availability": "Glynn County_Georgia, GA",
                "top_driver": false,
                "paid": true,
                "owner_driver": "Romelis Jimenez",
                "owner_phone": "(912) 603-3034",
                "owner_home_city": "Brunswick",
                "owner_email": "romelishjimenezl@gmail.com",
                "owner_home": "Georgia, GA",
                "type": "Cargo van",
                "lwh": "143\/55\/68",
                "payload_max": "4000",
                "city": "Glynn County",
                "comments": "",
                "vin_code": "3C6LRVDG6PE536192",
                "residentship": "Work Authorization",
                "driver_name": "Romelis Jimenez",
                "driver_phone": "(912) 603-3034",
                "driver_email": "romelishjimenezl@gmail.com",
                "driver2_name": "-",
                "driver2_phone": "",
                "driver2_email": "-",
                "main_contact": "(912) 603-3034",
                "driver_license": "071349897",
                "ein": "99-4313345",
                "company_name": "WITH FAITH N&H SERVICES LLC",
                "vehicle_year": "2023",
                "date_hr": "01\/05\/2024 6:12 pm",
                "id_hr": 113,
                "source_hr": "indeed",
                "nationality": "Venezuela",
                "google_drive": true,
                "emergency_contact": "Nancy Contreras de Jimenez",
                "emergency_phone": "(912) 603-3027",
                "select_labels": [
                    "ppe",
                    "real_id",
                    "macropoint",
                    "tucker-tools",
                    "printer"
                ],
                "select_labels_distance": [
                    "otr"
                ],
                "preferred_language_icon": "en"
            },
            "latitude": "31.3211",
            "longitude": "-81.526435",
            "updated_zipcode": "06\/09\/2025 11:39 am",
            "zipcode": "31525",
            "timecode": "1749469143",
            "last_update": "Last update: Leila Azhar - 06\/09\/2025 3:39 am",
            "date_timecode": "1749369600",
            "driver_rating": "[{\"name\":\"Victor Miller\",\"time\":1704994500,\"reit\":\"5\",\"mess\":\"\",\"order_number\":\"103366\"},{\"name\":\"Mark Adams\",\"time\":1705346580,\"reit\":\"5\",\"mess\":\"\",\"order_number\":\"28331370\"},{\"name\":\"Ben Silver\",\"time\":1706128380,\"reit\":\"5\",\"mess\":\"\",\"order_number\":\"14351829\"},{\"name\":\"John Ali\",\"time\":1708729500,\"reit\":\"5\",\"mess\":\"Very helpful \",\"order_number\":\"52395\"},{\"name\":\"Tracking \",\"time\":1708957560,\"reit\":\"5\",\"mess\":\"\",\"order_number\":\"118207515 \"},{\"name\":\"Jacob Kowalski\",\"time\":1717189560,\"reit\":\"5\",\"mess\":\"\",\"order_number\":\"150918\"},{\"name\":\"Victor Miller\",\"time\":1721924040,\"reit\":\"3\",\"mess\":\"covered 100 miles in the opposite direction for no reason. Load was DIRECT. \",\"order_number\":\"7129845\"},{\"name\":\"Paul Vinikourov\",\"time\":1733918160,\"reit\":\"5\",\"mess\":\"Good rate RTG good timing good communication good updates\",\"order_number\":\"30533908\"},{\"name\":\"Nona Allen\",\"time\":1738857900,\"reit\":\"5\",\"mess\":\"\",\"order_number\":\"4834993\"},{\"name\":\"Paul Vinikourov\",\"time\":1739970720,\"reit\":\"5\",\"mess\":\"Good rate RTG good timing good communication good updates\",\"order_number\":\"2260487\"},{\"name\":\"Paul Vinikourov\",\"time\":1743078420,\"reit\":\"5\",\"mess\":\"Good rate RTG good timing good communication good updates\",\"order_number\":\"S2902934\"}]",
            "warning": false,
            "checked_from_brokersnapshot": "1749399743",
            "check_mcdot_manual": false,
            "dot": false,
            "clean_background": false,
            "clean_check_date": "1734612978"
        }
    },
    {
        "ID": 1677,
        "fields": {
            "driver": {
                "status": {
                    "value": "available",
                    "label": "Available"
                },
                "date": "06\/08\/2025 2:00 pm",
                "availability": "Wyandotte County_Kansas, KS",
                "top_driver": false,
                "paid": true,
                "owner_driver": "Jhoan Cardenas",
                "owner_phone": "(862) 428-7384",
                "owner_home_city": "Brick",
                "owner_email": "sdhtransportationllc@gmail.com",
                "owner_home": "New Jersey, NJ",
                "type": "Cargo van",
                "lwh": "156\/54\/67",
                "payload_max": "3300",
                "city": "Kansas City",
                "comments": ".",
                "vin_code": "3C6MRVJG3PE502851",
                "residentship": "Green Card",
                "driver_name": "Jhoan Cardenas",
                "driver_phone": "(862) 271-6569",
                "driver_email": "sdhtransportationllc@gmail.com",
                "driver2_name": "",
                "driver2_phone": "",
                "driver2_email": "",
                "main_contact": "(862) 428-7384",
                "driver_license": "C0566-40166-11872",
                "ein": "92-2516627",
                "company_name": "SDH Transportation LLC",
                "vehicle_year": "2023",
                "date_hr": "01\/04\/2024 1:13 pm",
                "id_hr": 94,
                "source_hr": "indeed",
                "nationality": "Peruvian",
                "google_drive": true,
                "emergency_contact": "Pamela",
                "emergency_phone": "(973) 930-1458",
                "select_labels": [
                    "tsa",
                    "twic",
                    "ppe",
                    "e-track",
                    "canada",
                    "macropoint",
                    "tucker-tools",
                    "sleeper",
                    "printer"
                ],
                "select_labels_distance": [
                    "otr",
                    "any"
                ],
                "preferred_language_icon": "en"
            },
            "latitude": "39.165351",
            "longitude": "-94.829341",
            "updated_zipcode": "06\/09\/2025 1:49 pm",
            "zipcode": "Kansas City Kansas 66109",
            "clean_background": true,
            "clean_check_date": "1730035667",
            "timecode": "1749476982",
            "last_update": "Last update: Julia Donovan - 06\/09\/2025 8:31 am",
            "date_timecode": "1749391200",
            "driver_rating": "[{\"name\":\"Vlad Allen\",\"time\":1708833540,\"reit\":\"5\",\"mess\":\"Good rate. Good communications.\",\"order_number\":\"OGRE30024813 \"},{\"name\":\"Victor Miller\",\"time\":1715286420,\"reit\":\"5\",\"mess\":\"\",\"order_number\":\"4246762\"},{\"name\":\"Jacob Kowalski\",\"time\":1717189980,\"reit\":\"5\",\"mess\":\"\",\"order_number\":\"152833\"},{\"name\":\"Travis McMillan\",\"time\":1719410220,\"reit\":\"5\",\"mess\":\"\",\"order_number\":\"145988\"},{\"name\":\"Jessie Zalewski\",\"time\":1721332380,\"reit\":\"5\",\"mess\":\"\",\"order_number\":\"2265853\"},{\"name\":\"Paul Vinikourov\",\"time\":1730292180,\"reit\":\"5\",\"mess\":\"Good rate RTG good updates good timing good communication\",\"order_number\":\"25138\"},{\"name\":\"Travis McMillan\",\"time\":1733510040,\"reit\":\"5\",\"mess\":\"\",\"order_number\":\"121272579\"},{\"name\":\"Paul Vinikourov\",\"time\":1738425300,\"reit\":\"5\",\"mess\":\"Good rate RTG good timing good communication\",\"order_number\":\"152834-0\"},{\"name\":\"Eric Mayson\",\"time\":1743424080,\"reit\":\"5\",\"mess\":\"\",\"order_number\":\" 20204\"},{\"name\":\"Paul Vinikourov\",\"time\":1744203300,\"reit\":\"5\",\"mess\":\"Good rate RTG good timing good communication good updates direct run overnight\",\"order_number\":\"ILG-261580\"}]",
            "warning": false,
            "checked_from_brokersnapshot": "1749399784",
            "check_mcdot_manual": false,
            "dot": false
        }
    },
    {
        "ID": 1649,
        "fields": {
            "driver": {
                "status": {
                    "value": "loaded_enroute",
                    "label": "Loaded & Enroute"
                },
                "date": "06\/10\/2025 10:00 am",
                "availability": "Muskingum County_Ohio, OH",
                "top_driver": false,
                "paid": false,
                "owner_driver": "Rafael Zaragoza",
                "owner_phone": "(941) 318-0688",
                "owner_home_city": "Sarasota",
                "owner_email": "rafazc@hotmail.com",
                "owner_home": "Florida, FL",
                "type": "Cargo van",
                "lwh": "150\/53\/70",
                "payload_max": "4000",
                "city": "Zanesville",
                "comments": ".",
                "vin_code": "1FTBW3XM8KKA28329",
                "residentship": "Work Authorization",
                "driver_name": "Rafael Zaragoza",
                "driver_phone": "(941) 318-0688",
                "driver_email": "rafazc@hotmail.com",
                "driver2_name": "",
                "driver2_phone": "",
                "driver2_email": "",
                "main_contact": "(941) 318-0688",
                "driver_license": "Z622-720-81-376-0",
                "ein": "SSN",
                "company_name": "Individual",
                "vehicle_year": "2019",
                "date_hr": "12\/20\/2023 7:54 pm",
                "id_hr": false,
                "source_hr": "indeed",
                "nationality": "Mexican",
                "google_drive": true,
                "emergency_contact": "LORENA RIVEIRA",
                "emergency_phone": "(941) 301-3592",
                "select_labels": [
                    "ppe",
                    "real_id",
                    "macropoint",
                    "tucker-tools",
                    "sleeper"
                ],
                "select_labels_distance": [
                    "any"
                ],
                "preferred_language_icon": "es"
            },
            "latitude": "39.96922",
            "longitude": "-81.991033",
            "updated_zipcode": "06\/09\/2025 3:21 pm",
            "zipcode": "43701",
            "timecode": "1749482492",
            "last_update": "Last update: Jasmine Azhar - 06\/09\/2025 7:21 am",
            "date_timecode": "1749549600",
            "driver_rating": "[{\"name\":\"Rick Dohonov\",\"time\":1704403260,\"reit\":\"5\",\"mess\":\"\",\"order_number\":\"60106576905\"},{\"name\":\"Fred Thomas\",\"time\":1705165080,\"reit\":\"5\",\"mess\":\"Good rate responsible on time communication very good driver\",\"order_number\":\"26836279\"},{\"name\":\"Tracking \",\"time\":1708523940,\"reit\":\"5\",\"mess\":\"Good communication \",\"order_number\":\"2402A4601\"},{\"name\":\"John Ali\",\"time\":1719845220,\"reit\":\"5\",\"mess\":\"Good service \",\"order_number\":\"60107575071\"},{\"name\":\"Ben Silver\",\"time\":1723656300,\"reit\":\"5\",\"mess\":\"\",\"order_number\":\"62076\"},{\"name\":\"Tracking \",\"time\":1724431140,\"reit\":\"5\",\"mess\":\"\",\"order_number\":\"0458329\"},{\"name\":\"Eric Mayson\",\"time\":1724880360,\"reit\":\"5\",\"mess\":\"\",\"order_number\":\"0458329\"},{\"name\":\"Paul Vinikourov\",\"time\":1737117720,\"reit\":\"5\",\"mess\":\"Good rate RTG good timing good updates a bit bad english\",\"order_number\":\"1926369\"},{\"name\":\"Nona Allen\",\"time\":1741623780,\"reit\":\"5\",\"mess\":\"\",\"order_number\":\"1852986\"},{\"name\":\"Terry Abdulaev\",\"time\":1743448620,\"reit\":\"5\",\"mess\":\"\",\"order_number\":\"1852986\"},{\"name\":\"Terry Abdulaev\",\"time\":1743449340,\"reit\":\"5\",\"mess\":\"\",\"order_number\":\"1872487\"},{\"name\":\"Ben Silver\",\"time\":1748620740,\"reit\":\"5\",\"mess\":\"\",\"order_number\":\" 1476333\"}]",
            "warning": false,
            "dot": false,
            "checked_from_brokersnapshot": "1749400949",
            "check_mcdot_manual": false,
            "clean_background": false,
            "clean_check_date": "1738157694"
        }
    }
]